Workbook

Sheet Healthcare_Sales_Dataset
A1: OrderID | B1: Product | C1: Region | D1: Salesperson | E1: UnitsSold | F1: UnitPrice | G1: Discount (%) | H1: ReturnStatus | I1: OrderDate | J1: TotalSales | K1: Deducations | L1: ExpectedSales | M1: Day | N1: Month | O1: Year | P1: PriceTag | Q1: SalesTag | R1: DiscountTag | S1: ReturnTag | T1: RegionCode
A2: ORD0001 | B2: Syringe Pack | C2: South | D2: Henry Davis | E2: 6 | F2: 500 | G2: 10 | H2: No | I2: 44986 | J2: =E2*F2*(1-G2/100) -> 2700 | K2: =ROUND(J2*15%,2) -> 405 | L2: =E2*F2 -> 3000 | M2: =DAY(I2) -> 1 | N2: =MONTH(I2) -> 3 | O2: =YEAR(I2) -> 2023 | P2: =IF(F2<500,"Low Price","High Price") -> High Price | Q2: =IF(J2>=AVERAGE(J:J),"Good","Bad") -> Bad | R2: =IF(G2>10,"High Discount",IF(G2=0,"No Discount","Low Discont")) -> Low Discont | S2: =IF(AND(H2="Yes",G2>10),"High Priority Review",IF(H2="Yes","Low Priority Review","No Review Needed")) -> No Review Needed | T2: =LEFT(C2,2) -> So
A3: ORD0002 | B3: Syringe Pack | C3: North | D3: Catherine Lee | E3: 3 | F3: 500 | G3: 10 | H3: No | I3: 44986 | J3: =E3*F3*(1-G3/100) -> 1350 | K3: =ROUND(J3*15%,2) -> 202.5 | L3: =E3*F3 -> 1500 | M3: =DAY(I3) -> 1 | N3: =MONTH(I3) -> 3 | O3: =YEAR(I3) -> 2023 | P3: =IF(F3<500,"Low Price","High Price") -> High Price | Q3: =IF(J3>=AVERAGE(J:J),"Good","Bad") -> Bad | R3: =IF(G3>10,"High Discount",IF(G3=0,"No Discount","Low Discont")) -> Low Discont | S3: =IF(AND(H3="Yes",G3>10),"High Priority Review",IF(H3="Yes","Low Priority Review","No Review Needed")) -> No Review Needed | T3: =LEFT(C3,2) -> No
A4: ORD0003 | B4: X-Ray Machine | C4: West | D4: David Miller | E4: 9 | F4: 5000 | G4: 10 | H4: Yes | I4: 45047 | J4: =E4*F4*(1-G4/100) -> 40500 | K4: =ROUND(J4*15%,2) -> 6075 | L4: =E4*F4 -> 45000 | M4: =DAY(I4) -> 1 | N4: =MONTH(I4) -> 5 | O4: =YEAR(I4) -> 2023 | P4: =IF(F4<500,"Low Price","High Price") -> High Price | Q4: =IF(J4>=AVERAGE(J:J),"Good","Bad") -> Good | R4: =IF(G4>10,"High Discount",IF(G4=0,"No Discount","Low Discont")) -> Low Discont | S4: =IF(AND(H4="Yes",G4>10),"High Priority Review",IF(H4="Yes","Low Priority Review","No Review Needed")) -> Low Priority Review | T4: =LEFT(C4,2) -> We
A5: ORD0004 | B5: Ultrasound Device | C5: West | D5: David Miller | E5: 2 | F5: 2000 | G5: 5 | H5: Yes | I5: 45078 | J5: =E5*F5*(1-G5/100) -> 3800 | K5: =ROUND(J5*15%,2) -> 570 | L5: =E5*F5 -> 4000 | M5: =DAY(I5) -> 1 | N5: =MONTH(I5) -> 6 | O5: =YEAR(I5) -> 2023 | P5: =IF(F5<500,"Low Price","High Price") -> High Price | Q5: =IF(J5>=AVERAGE(J:J),"Good","Bad") -> Bad | R5: =IF(G5>10,"High Discount",IF(G5=0,"No Discount","Low Discont")) -> Low Discont | S5: =IF(AND(H5="Yes",G5>10),"High Priority Review",IF(H5="Yes","Low Priority Review","No Review Needed")) -> Low Priority Review | T5: =LEFT(C5,2) -> We
A6: ORD0005 | B6: Stethoscope | C6: East | E6: 3 | F6: 750 | G6: 5 | H6: Yes | I6: 45139 | J6: =E6*F6*(1-G6/100) -> 2137.5 | K6: =ROUND(J6*15%,2) -> 320.63 | L6: =E6*F6 -> 2250 | M6: =DAY(I6) -> 1 | N6: =MONTH(I6) -> 8 | O6: =YEAR(I6) -> 2023 | P6: =IF(F6<500,"Low Price","High Price") -> High Price | Q6: =IF(J6>=AVERAGE(J:J),"Good","Bad") -> Bad | R6: =IF(G6>10,"High Discount",IF(G6=0,"No Discount","Low Discont")) -> Low Discont | S6: =IF(AND(H6="Yes",G6>10),"High Priority Review",IF(H6="Yes","Low Priority Review","No Review Needed")) -> Low Priority Review | T6: =LEFT(C6,2) -> Ea
A7: ORD0006 | B7: Thermometer | C7: North | D7: Catherine Lee | E7: 14 | F7: 250 | G7: 10 | H7: No | I7: 45139 | J7: =E7*F7*(1-G7/100) -> 3150 | K7: =ROUND(J7*15%,2) -> 472.5 | L7: =E7*F7 -> 3500 | M7: =DAY(I7) -> 1 | N7: =MONTH(I7) -> 8 | O7: =YEAR(I7) -> 2023 | P7: =IF(F7<500,"Low Price","High Price") -> Low Price | Q7: =IF(J7>=AVERAGE(J:J),"Good","Bad") -> Bad | R7: =IF(G7>10,"High Discount",IF(G7=0,"No Discount","Low Discont")) -> Low Discont | S7: =IF(AND(H7="Yes",G7>10),"High Priority Review",IF(H7="Yes","Low Priority Review","No Review Needed")) -> No Review Needed | T7: =LEFT(C7,2) -> No
A8: ORD0007 | B8: Thermometer | C8: East | D8: Grace Kim | E8: 25 | F8: 250 | G8: 15 | H8: No | I8: 45139 | J8: =E8*F8*(1-G8/100) -> 5312.5 | K8: =ROUND(J8*15%,2) -> 796.88 | L8: =E8*F8 -> 6250 | M8: =DAY(I8) -> 1 | N8: =MONTH(I8) -> 8 | O8: =YEAR(I8) -> 2023 | P8: =IF(F8<500,"Low Price","High Price") -> Low Price | Q8: =IF(J8>=AVERAGE(J:J),"Good","Bad") -> Bad | R8: =IF(G8>10,"High Discount",IF(G8=0,"No Discount","Low Discont")) -> High Discount | S8: =IF(AND(H8="Yes",G8>10),"High Priority Review",IF(H8="Yes","Low Priority Review","No Review Needed")) -> No Review Needed | T8: =LEFT(C8,2) -> Ea
A9: ORD0008 | B9: Blood Test Kit | C9: North | D9: Eva Brown | E9: 49 | F9: 1750 | G9: 15 | H9: Yes | I9: 45200 | J9: =E9*F9*(1-G9/100) -> 72887.5 | K9: =ROUND(J9*15%,2) -> 10933.13 | L9: =E9*F9 -> 85750 | M9: =DAY(I9) -> 1 | N9: =MONTH(I9) -> 10 | O9: =YEAR(I9) -> 2023 | P9: =IF(F9<500,"Low Price","High Price") -> High Price | Q9: =IF(J9>=AVERAGE(J:J),"Good","Bad") -> Good | R9: =IF(G9>10,"High Discount",IF(G9=0,"No Discount","Low Discont")) -> High Discount | S9: =IF(AND(H9="Yes",G9>10),"High Priority Review",IF(H9="Yes","Low Priority Review","No Review Needed")) -> High Priority Review | T9: =LEFT(C9,2) -> No
A10: ORD0009 | B10: Stethoscope | C10: North | D10: Catherine Lee | E10: 10 | F10: 750 | G10: 5 | H10: No | I10: 45231 | J10: =E10*F10*(1-G10/100) -> 7125 | K10: =ROUND(J10*15%,2) -> 1068.75 | L10: =E10*F10 -> 7500 | M10: =DAY(I10) -> 1 | N10: =MONTH(I10) -> 11 | O10: =YEAR(I10) -> 2023 | P10: =IF(F10<500,"Low Price","High Price") -> High Price | Q10: =IF(J10>=AVERAGE(J:J),"Good","Bad") -> Bad | R10: =IF(G10>10,"High Discount",IF(G10=0,"No Discount","Low Discont")) -> Low Discont | S10: =IF(AND(H10="Yes",G10>10),"High Priority Review",IF(H10="Yes","Low Priority Review","No Review Needed")) -> No Review Needed | T10: =LEFT(C10,2) -> No
A11: ORD0010 | B11: Stethoscope | C11: East | D11: Alice Johnson | E11: 14 | F11: 750 | G11: 15 | H11: Yes | I11: 44959 | J11: =E11*F11*(1-G11/100) -> 8925 | K11: =ROUND(J11*15%,2) -> 1338.75 | L11: =E11*F11 -> 10500 | M11: =DAY(I11) -> 2 | N11: =MONTH(I11) -> 2 | O11: =YEAR(I11) -> 2023 | P11: =IF(F11<500,"Low Price","High Price") -> High Price | Q11: =IF(J11>=AVERAGE(J:J),"Good","Bad") -> Bad | R11: =IF(G11>10,"High Discount",IF(G11=0,"No Discount","Low Discont")) -> High Discount | S11: =IF(AND(H11="Yes",G11>10),"High Priority Review",IF(H11="Yes","Low Priority Review","No Review Needed")) -> High Priority Review | T11: =LEFT(C11,2) -> Ea
A12: ORD0011 | B12: X-Ray Machine | C12: West | D12: David Miller | E12: 6 | F12: 5000 | G12: 20 | H12: No | I12: 44959 | J12: =E12*F12*(1-G12/100) -> 24000 | K12: =ROUND(J12*15%,2) -> 3600 | L12: =E12*F12 -> 30000 | M12: =DAY(I12) -> 2 | N12: =MONTH(I12) -> 2 | O12: =YEAR(I12) -> 2023 | P12: =IF(F12<500,"Low Price","High Price") -> High Price | Q12: =IF(J12>=AVERAGE(J:J),"Good","Bad") -> Good | R12: =IF(G12>10,"High Discount",IF(G12=0,"No Discount","Low Discont")) -> High Discount | S12: =IF(AND(H12="Yes",G12>10),"High Priority Review",IF(H12="Yes","Low Priority Review","No Review Needed")) -> No Review Needed | T12: =LEFT(C12,2) -> We
A13: ORD0012 | B13: Thermometer | C13: East | D13: Alice Johnson | E13: 21 | F13: 250 | G13: 5 | H13: No | I13: 45109 | J13: =E13*F13*(1-G13/100) -> 4987.5 | K13: =ROUND(J13*15%,2) -> 748.13 | L13: =E13*F13 -> 5250 | M13: =DAY(I13) -> 2 | N13: =MONTH(I13) -> 7 | O13: =YEAR(I13) -> 2023 | P13: =IF(F13<500,"Low Price","High Price") -> Low Price | Q13: =IF(J13>=AVERAGE(J:J),"Good","Bad") -> Bad | R13: =IF(G13>10,"High Discount",IF(G13=0,"No Discount","Low Discont")) -> Low Discont | S13: =IF(AND(H13="Yes",G13>10),"High Priority Review",IF(H13="Yes","Low Priority Review","No Review Needed")) -> No Review Needed | T13: =LEFT(C13,2) -> Ea
A14: ORD0013 | B14: Syringe Pack | C14: East | D14: Grace Kim | E14: 32 | F14: 500 | G14: 5 | H14: Yes | I14: 45262 | J14: =E14*F14*(1-G14/100) -> 15200 | K14: =ROUND(J14*15%,2) -> 2280 | L14: =E14*F14 -> 16000 | M14: =DAY(I14) -> 2 | N14: =MONTH(I14) -> 12 | O14: =YEAR(I14) -> 2023 | P14: =IF(F14<500,"Low Price","High Price") -> High Price | Q14: =IF(J14>=AVERAGE(J:J),"Good","Bad") -> Bad | R14: =IF(G14>10,"High Discount",IF(G14=0,"No Discount","Low Discont")) -> Low Discont | S14: =IF(AND(H14="Yes",G14>10),"High Priority Review",IF(H14="Yes","Low Priority Review","No Review Needed")) -> Low Priority Review | T14: =LEFT(C14,2) -> Ea
A15: ORD0014 | B15: X-Ray Machine | C15: North | D15: Eva Brown | E15: 7 | F15: 5000 | G15: 20 | H15: Yes | I15: 45262 | J15: =E15*F15*(1-G15/100) -> 28000 | K15: =ROUND(J15*15%,2) -> 4200 | L15: =E15*F15 -> 35000 | M15: =DAY(I15) -> 2 | N15: =MONTH(I15) -> 12 | O15: =YEAR(I15) -> 2023 | P15: =IF(F15<500,"Low Price","High Price") -> High Price | Q15: =IF(J15>=AVERAGE(J:J),"Good","Bad") -> Good | R15: =IF(G15>10,"High Discount",IF(G15=0,"No Discount","Low Discont")) -> High Discount | S15: =IF(AND(H15="Yes",G15>10),"High Priority Review",IF(H15="Yes","Low Priority Review","No Review Needed")) -> High Priority Review | T15: =LEFT(C15,2) -> No
A16: ORD0015 | B16: Ultrasound Device | C16: South | D16: Henry Davis | E16: 5 | F16: 2000 | G16: 10 | H16: Yes | I16: 44988 | J16: =E16*F16*(1-G16/100) -> 9000 | K16: =ROUND(J16*15%,2) -> 1350 | L16: =E16*F16 -> 10000 | M16: =DAY(I16) -> 3 | N16: =MONTH(I16) -> 3 | O16: =YEAR(I16) -> 2023 | P16: =IF(F16<500,"Low Price","High Price") -> High Price | Q16: =IF(J16>=AVERAGE(J:J),"Good","Bad") -> Bad | R16: =IF(G16>10,"High Discount",IF(G16=0,"No Discount","Low Discont")) -> Low Discont | S16: =IF(AND(H16="Yes",G16>10),"High Priority Review",IF(H16="Yes","Low Priority Review","No Review Needed")) -> Low Priority Review | T16: =LEFT(C16,2) -> So
A17: ORD0016 | B17: Insulin Pump | C17: North | D17: Catherine Lee | E17: 49 | F17: 1000 | G17: 10 | H17: No | I17: 44988 | J17: =E17*F17*(1-G17/100) -> 44100 | K17: =ROUND(J17*15%,2) -> 6615 | L17: =E17*F17 -> 49000 | M17: =DAY(I17) -> 3 | N17: =MONTH(I17) -> 3 | O17: =YEAR(I17) -> 2023 | P17: =IF(F17<500,"Low Price","High Price") -> High Price | Q17: =IF(J17>=AVERAGE(J:J),"Good","Bad") -> Good | R17: =IF(G17>10,"High Discount",IF(G17=0,"No Discount","Low Discont")) -> Low Discont | S17: =IF(AND(H17="Yes",G17>10),"High Priority Review",IF(H17="Yes","Low Priority Review","No Review Needed")) -> No Review Needed | T17: =LEFT(C17,2) -> No
A18: ORD0017 | B18: Insulin Pump | C18: North | D18: Catherine Lee | E18: 31 | F18: 1000 | G18: 15 | H18: No | I18: 45019 | J18: =E18*F18*(1-G18/100) -> 26350 | K18: =ROUND(J18*15%,2) -> 3952.5 | L18: =E18*F18 -> 31000 | M18: =DAY(I18) -> 3 | N18: =MONTH(I18) -> 4 | O18: =YEAR(I18) -> 2023 | P18: =IF(F18<500,"Low Price","High Price") -> High Price | Q18: =IF(J18>=AVERAGE(J:J),"Good","Bad") -> Good | R18: =IF(G18>10,"High Discount",IF(G18=0,"No Discount","Low Discont")) -> High Discount | S18: =IF(AND(H18="Yes",G18>10),"High Priority Review",IF(H18="Yes","Low Priority Review","No Review Needed")) -> No Review Needed | T18: =LEFT(C18,2) -> No
... A20: ORD0019 | B20: Blood Test Kit | C20: North | D20: Eva Brown | E20: 30 | F20: 1750 | G20: 0 | H20: Yes | I20: 45172 | J20: =E20*F20*(1-G20/100) -> 52500 | K20: =ROUND(J20*15%,2) -> 7875 | L20: =E20*F20 -> 52500 | M20: =DAY(I20) -> 3 | N20: =MONTH(I20) -> 9 | O20: =YEAR(I20) -> 2023 | P20: =IF(F20<500,"Low Price","High Price") -> High Price | Q20: =IF(J20>=AVERAGE(J:J),"Good","Bad") -> Good | R20: =IF(G20>10,"High Discount",IF(G20=0,"No Discount","Low Discont")) -> No Discount | S20: =IF(AND(H20="Yes",G20>10),"High Priority Review",IF(H20="Yes","Low Priority Review","No Review Needed")) -> Low Priority Review | T20: =LEFT(C20,2) -> No
A21: ORD0020 | B21: Thermometer | C21: East | D21: Grace Kim | E21: 7 | F21: 250 | H21: No | I21: 44961 | J21: =E21*F21*(1-G21/100) -> 1750 | K21: =ROUND(J21*15%,2) -> 262.5 | L21: =E21*F21 -> 1750 | M21: =DAY(I21) -> 4 | N21: =MONTH(I21) -> 2 | O21: =YEAR(I21) -> 2023 | P21: =IF(F21<500,"Low Price","High Price") -> Low Price | Q21: =IF(J21>=AVERAGE(J:J),"Good","Bad") -> Bad | R21: =IF(G21>10,"High Discount",IF(G21=0,"No Discount","Low Discont")) -> No Discount | S21: =IF(AND(H21="Yes",G21>10),"High Priority Review",IF(H21="Yes","Low Priority Review","No Review Needed")) -> No Review Needed | T21: =LEFT(C21,2) -> Ea
A22: ORD0021 | B22: Blood Test Kit | C22: East | D22: Grace Kim | E22: 8 | F22: 1750 | G22: 10 | H22: Yes | I22: 45081 | J22: =E22*F22*(1-G22/100) -> 12600 | K22: =ROUND(J22*15%,2) -> 1890 | L22: =E22*F22 -> 14000 | M22: =DAY(I22) -> 4 | N22: =MONTH(I22) -> 6 | O22: =YEAR(I22) -> 2023 | P22: =IF(F22<500,"Low Price","High Price") -> High Price | Q22: =IF(J22>=AVERAGE(J:J),"Good","Bad") -> Bad | R22: =IF(G22>10,"High Discount",IF(G22=0,"No Discount","Low Discont")) -> Low Discont | S22: =IF(AND(H22="Yes",G22>10),"High Priority Review",IF(H22="Yes","Low Priority Review","No Review Needed")) -> Low Priority Review | T22: =LEFT(C22,2) -> Ea
A23: ORD0022 | B23: Blood Test Kit | C23: West | D23: David Miller | E23: 9 | F23: 1750 | G23: 15 | H23: Yes | I23: 45111 | J23: =E23*F23*(1-G23/100) -> 13387.5 | K23: =ROUND(J23*15%,2) -> 2008.13 | L23: =E23*F23 -> 15750 | M23: =DAY(I23) -> 4 | N23: =MONTH(I23) -> 7 | O23: =YEAR(I23) -> 2023 | P23: =IF(F23<500,"Low Price","High Price") -> High Price | Q23: =IF(J23>=AVERAGE(J:J),"Good","Bad") -> Bad | R23: =IF(G23>10,"High Discount",IF(G23=0,"No Discount","Low Discont")) -> High Discount | S23: =IF(AND(H23="Yes",G23>10),"High Priority Review",IF(H23="Yes","Low Priority Review","No Review Needed")) -> High Priority Review | T23: =LEFT(C23,2) -> We
A24: ORD0023 | B24: Insulin Pump | C24: North | D24: Catherine Lee | E24: 38 | F24: 1000 | G24: 5 | H24: Yes | I24: 45264 | J24: =E24*F24*(1-G24/100) -> 36100 | K24: =ROUND(J24*15%,2) -> 5415 | L24: =E24*F24 -> 38000 | M24: =DAY(I24) -> 4 | N24: =MONTH(I24) -> 12 | O24: =YEAR(I24) -> 2023 | P24: =IF(F24<500,"Low Price","High Price") -> High Price | Q24: =IF(J24>=AVERAGE(J:J),"Good","Bad") -> Good | R24: =IF(G24>10,"High Discount",IF(G24=0,"No Discount","Low Discont")) -> Low Discont | S24: =IF(AND(H24="Yes",G24>10),"High Priority Review",IF(H24="Yes","Low Priority Review","No Review Needed")) -> Low Priority Review | T24: =LEFT(C24,2) -> No
A25: ORD0024 | B25: Ultrasound Device | C25: North | D25: Eva Brown | E25: 3 | F25: 2000 | G25: 5 | H25: Yes | I25: 45112 | J25: =E25*F25*(1-G25/100) -> 5700 | K25: =ROUND(J25*15%,2) -> 855 | L25: =E25*F25 -> 6000 | M25: =DAY(I25) -> 5 | N25: =MONTH(I25) -> 7 | O25: =YEAR(I25) -> 2023 | P25: =IF(F25<500,"Low Price","High Price") -> High Price | Q25: =IF(J25>=AVERAGE(J:J),"Good","Bad") -> Bad | R25: =IF(G25>10,"High Discount",IF(G25=0,"No Discount","Low Discont")) -> Low Discont | S25: =IF(AND(H25="Yes",G25>10),"High Priority Review",IF(H25="Yes","Low Priority Review","No Review Needed")) -> Low Priority Review | T25: =LEFT(C25,2) -> No
A26: ORD0025 | B26: Stethoscope | C26: East | D26: Alice Johnson | E26: 6 | F26: 750 | G26: 10 | H26: No | I26: 45265 | J26: =E26*F26*(1-G26/100) -> 4050 | K26: =ROUND(J26*15%,2) -> 607.5 | L26: =E26*F26 -> 4500 | M26: =DAY(I26) -> 5 | N26: =MONTH(I26) -> 12 | O26: =YEAR(I26) -> 2023 | P26: =IF(F26<500,"Low Price","High Price") -> High Price | Q26: =IF(J26>=AVERAGE(J:J),"Good","Bad") -> Bad | R26: =IF(G26>10,"High Discount",IF(G26=0,"No Discount","Low Discont")) -> Low Discont | S26: =IF(AND(H26="Yes",G26>10),"High Priority Review",IF(H26="Yes","Low Priority Review","No Review Needed")) -> No Review Needed | T26: =LEFT(C26,2) -> Ea
A27: ORD0026 | B27: Thermometer | C27: East | D27: Alice Johnson | E27: 14 | F27: 250 | G27: 10 | H27: No | I27: 44963 | J27: =E27*F27*(1-G27/100) -> 3150 | K27: =ROUND(J27*15%,2) -> 472.5 | L27: =E27*F27 -> 3500 | M27: =DAY(I27) -> 6 | N27: =MONTH(I27) -> 2 | O27: =YEAR(I27) -> 2023 | P27: =IF(F27<500,"Low Price","High Price") -> Low Price | Q27: =IF(J27>=AVERAGE(J:J),"Good","Bad") -> Bad | R27: =IF(G27>10,"High Discount",IF(G27=0,"No Discount","Low Discont")) -> Low Discont | S27: =IF(AND(H27="Yes",G27>10),"High Priority Review",IF(H27="Yes","Low Priority Review","No Review Needed")) -> No Review Needed | T27: =LEFT(C27,2) -> Ea
A28: ORD0027 | B28: X-Ray Machine | C28: East | D28: Alice Johnson | E28: 9 | F28: 5000 | G28: 10 | H28: Yes | I28: 44991 | J28: =E28*F28*(1-G28/100) -> 40500 | K28: =ROUND(J28*15%,2) -> 6075 | L28: =E28*F28 -> 45000 | M28: =DAY(I28) -> 6 | N28: =MONTH(I28) -> 3 | O28: =YEAR(I28) -> 2023 | P28: =IF(F28<500,"Low Price","High Price") -> High Price | Q28: =IF(J28>=AVERAGE(J:J),"Good","Bad") -> Good | R28: =IF(G28>10,"High Discount",IF(G28=0,"No Discount","Low Discont")) -> Low Discont | S28: =IF(AND(H28="Yes",G28>10),"High Priority Review",IF(H28="Yes","Low Priority Review","No Review Needed")) -> Low Priority Review | T28: =LEFT(C28,2) -> Ea
A29: ORD0028 | B29: Stethoscope | C29: North | D29: Catherine Lee | E29: 3 | F29: 750 | G29: 15 | H29: Yes | I29: 44991 | J29: =E29*F29*(1-G29/100) -> 1912.5 | K29: =ROUND(J29*15%,2) -> 286.88 | L29: =E29*F29 -> 2250 | M29: =DAY(I29) -> 6 | N29: =MONTH(I29) -> 3 | O29: =YEAR(I29) -> 2023 | P29: =IF(F29<500,"Low Price","High Price") -> High Price | Q29: =IF(J29>=AVERAGE(J:J),"Good","Bad") -> Bad | R29: =IF(G29>10,"High Discount",IF(G29=0,"No Discount","Low Discont")) -> High Discount | S29: =IF(AND(H29="Yes",G29>10),"High Priority Review",IF(H29="Yes","Low Priority Review","No Review Needed")) -> High Priority Review | T29: =LEFT(C29,2) -> No
A30: ORD0029 | B30: Insulin Pump | C30: North | D30: Eva Brown | E30: 13 | F30: 1000 | G30: 20 | H30: No | I30: 44991 | J30: =E30*F30*(1-G30/100) -> 10400 | K30: =ROUND(J30*15%,2) -> 1560 | L30: =E30*F30 -> 13000 | M30: =DAY(I30) -> 6 | N30: =MONTH(I30) -> 3 | O30: =YEAR(I30) -> 2023 | P30: =IF(F30<500,"Low Price","High Price") -> High Price | Q30: =IF(J30>=AVERAGE(J:J),"Good","Bad") -> Bad | R30: =IF(G30>10,"High Discount",IF(G30=0,"No Discount","Low Discont")) -> High Discount | S30: =IF(AND(H30="Yes",G30>10),"High Priority Review",IF(H30="Yes","Low Priority Review","No Review Needed")) -> No Review Needed | T30: =LEFT(C30,2) -> No
A31: ORD0030 | B31: Insulin Pump | C31: East | D31: Alice Johnson | E31: 40 | F31: 1000 | G31: 5 | H31: No | I31: 45022 | J31: =E31*F31*(1-G31/100) -> 38000 | K31: =ROUND(J31*15%,2) -> 5700 | L31: =E31*F31 -> 40000 | M31: =DAY(I31) -> 6 | N31: =MONTH(I31) -> 4 | O31: =YEAR(I31) -> 2023 | P31: =IF(F31<500,"Low Price","High Price") -> High Price | Q31: =IF(J31>=AVERAGE(J:J),"Good","Bad") -> Good | R31: =IF(G31>10,"High Discount",IF(G31=0,"No Discount","Low Discont")) -> Low Discont | S31: =IF(AND(H31="Yes",G31>10),"High Priority Review",IF(H31="Yes","Low Priority Review","No Review Needed")) -> No Review Needed | T31: =LEFT(C31,2) -> Ea
A32: ORD0031 | B32: Ultrasound Device | C32: North | D32: Eva Brown | E32: 5 | F32: 2000 | G32: 15 | H32: Yes | I32: 45052 | J32: =E32*F32*(1-G32/100) -> 8500 | K32: =ROUND(J32*15%,2) -> 1275 | L32: =E32*F32 -> 10000 | M32: =DAY(I32) -> 6 | N32: =MONTH(I32) -> 5 | O32: =YEAR(I32) -> 2023 | P32: =IF(F32<500,"Low Price","High Price") -> High Price | Q32: =IF(J32>=AVERAGE(J:J),"Good","Bad") -> Bad | R32: =IF(G32>10,"High Discount",IF(G32=0,"No Discount","Low Discont")) -> High Discount | S32: =IF(AND(H32="Yes",G32>10),"High Priority Review",IF(H32="Yes","Low Priority Review","No Review Needed")) -> High Priority Review | T32: =LEFT(C32,2) -> No
A33: ORD0032 | B33: Blood Test Kit | C33: South | D33: Henry Davis | E33: 29 | F33: 1750 | G33: 20 | H33: No | I33: 45083 | J33: =E33*F33*(1-G33/100) -> 40600 | K33: =ROUND(J33*15%,2) -> 6090 | L33: =E33*F33 -> 50750 | M33: =DAY(I33) -> 6 | N33: =MONTH(I33) -> 6 | O33: =YEAR(I33) -> 2023 | P33: =IF(F33<500,"Low Price","High Price") -> High Price | Q33: =IF(J33>=AVERAGE(J:J),"Good","Bad") -> Good | R33: =IF(G33>10,"High Discount",IF(G33=0,"No Discount","Low Discont")) -> High Discount | S33: =IF(AND(H33="Yes",G33>10),"High Priority Review",IF(H33="Yes","Low Priority Review","No Review Needed")) -> No Review Needed | T33: =LEFT(C33,2) -> So
... A54: ORD0053 | B54: Ultrasound Device | C54: North | D54: Eva Brown | E54: 1 | F54: 2000 | G54: 15 | H54: Yes | I54: 45238 | J54: =E54*F54*(1-G54/100) -> 1700 | K54: =ROUND(J54*15%,2) -> 255 | L54: =E54*F54 -> 2000 | M54: =DAY(I54) -> 8 | N54: =MONTH(I54) -> 11 | O54: =YEAR(I54) -> 2023 | P54: =IF(F54<500,"Low Price","High Price") -> High Price | Q54: =IF(J54>=AVERAGE(J:J),"Good","Bad") -> Bad | R54: =IF(G54>10,"High Discount",IF(G54=0,"No Discount","Low Discont")) -> High Discount | S54: =IF(AND(H54="Yes",G54>10),"High Priority Review",IF(H54="Yes","Low Priority Review","No Review Needed")) -> High Priority Review | T54: =LEFT(C54,2) -> No
A55: ORD0054 | B55: X-Ray Machine | C55: North | D55: Catherine Lee | E55: 4 | F55: 5000 | H55: No | I55: 45268 | J55: =E55*F55*(1-G55/100) -> 20000 | K55: =ROUND(J55*15%,2) -> 3000 | L55: =E55*F55 -> 20000 | M55: =DAY(I55) -> 8 | N55: =MONTH(I55) -> 12 | O55: =YEAR(I55) -> 2023 | P55: =IF(F55<500,"Low Price","High Price") -> High Price | Q55: =IF(J55>=AVERAGE(J:J),"Good","Bad") -> Good | R55: =IF(G55>10,"High Discount",IF(G55=0,"No Discount","Low Discont")) -> No Discount | S55: =IF(AND(H55="Yes",G55>10),"High Priority Review",IF(H55="Yes","Low Priority Review","No Review Needed")) -> No Review Needed | T55: =LEFT(C55,2) -> No
A56: ORD0055 | B56: PPE Kit | C56: East | D56: Alice Johnson | E56: 16 | F56: 3000 | G56: 5 | H56: No | I56: 44935 | J56: =E56*F56*(1-G56/100) -> 45600 | K56: =ROUND(J56*15%,2) -> 6840 | L56: =E56*F56 -> 48000 | M56: =DAY(I56) -> 9 | N56: =MONTH(I56) -> 1 | O56: =YEAR(I56) -> 2023 | P56: =IF(F56<500,"Low Price","High Price") -> High Price | Q56: =IF(J56>=AVERAGE(J:J),"Good","Bad") -> Good | R56: =IF(G56>10,"High Discount",IF(G56=0,"No Discount","Low Discont")) -> Low Discont | S56: =IF(AND(H56="Yes",G56>10),"High Priority Review",IF(H56="Yes","Low Priority Review","No Review Needed")) -> No Review Needed | T56: =LEFT(C56,2) -> Ea
A57: ORD0056 | B57: Blood Test Kit | C57: South | D57: Henry Davis | E57: 41 | F57: 1750 | G57: 10 | H57: No | I57: 44966 | J57: =E57*F57*(1-G57/100) -> 64575 | K57: =ROUND(J57*15%,2) -> 9686.25 | L57: =E57*F57 -> 71750 | M57: =DAY(I57) -> 9 | N57: =MONTH(I57) -> 2 | O57: =YEAR(I57) -> 2023 | P57: =IF(F57<500,"Low Price","High Price") -> High Price | Q57: =IF(J57>=AVERAGE(J:J),"Good","Bad") -> Good | R57: =IF(G57>10,"High Discount",IF(G57=0,"No Discount","Low Discont")) -> Low Discont | S57: =IF(AND(H57="Yes",G57>10),"High Priority Review",IF(H57="Yes","Low Priority Review","No Review Needed")) -> No Review Needed | T57: =LEFT(C57,2) -> So
A58: ORD0057 | B58: Insulin Pump | C58: East | D58: Grace Kim | E58: 11 | F58: 1000 | G58: 5 | H58: Yes | I58: 45055 | J58: =E58*F58*(1-G58/100) -> 10450 | K58: =ROUND(J58*15%,2) -> 1567.5 | L58: =E58*F58 -> 11000 | M58: =DAY(I58) -> 9 | N58: =MONTH(I58) -> 5 | O58: =YEAR(I58) -> 2023 | P58: =IF(F58<500,"Low Price","High Price") -> High Price | Q58: =IF(J58>=AVERAGE(J:J),"Good","Bad") -> Bad | R58: =IF(G58>10,"High Discount",IF(G58=0,"No Discount","Low Discont")) -> Low Discont | S58: =IF(AND(H58="Yes",G58>10),"High Priority Review",IF(H58="Yes","Low Priority Review","No Review Needed")) -> Low Priority Review | T58: =LEFT(C58,2) -> Ea
A59: ORD0058 | B59: Insulin Pump | C59: North | D59: Catherine Lee | E59: 39 | F59: 1000 | G59: 0 | H59: Yes | I59: 45086 | J59: =E59*F59*(1-G59/100) -> 39000 | K59: =ROUND(J59*15%,2) -> 5850 | L59: =E59*F59 -> 39000 | M59: =DAY(I59) -> 9 | N59: =MONTH(I59) -> 6 | O59: =YEAR(I59) -> 2023 | P59: =IF(F59<500,"Low Price","High Price") -> High Price | Q59: =IF(J59>=AVERAGE(J:J),"Good","Bad") -> Good | R59: =IF(G59>10,"High Discount",IF(G59=0,"No Discount","Low Discont")) -> No Discount | S59: =IF(AND(H59="Yes",G59>10),"High Priority Review",IF(H59="Yes","Low Priority Review","No Review Needed")) -> Low Priority Review | T59: =LEFT(C59,2) -> No
A60: ORD0059 | B60: Insulin Pump | C60: East | D60: Grace Kim | E60: 27 | F60: 1000 | G60: 0 | H60: Yes | I60: 45147 | J60: =E60*F60*(1-G60/100) -> 27000 | K60: =ROUND(J60*15%,2) -> 4050 | L60: =E60*F60 -> 27000 | M60: =DAY(I60) -> 9 | N60: =MONTH(I60) -> 8 | O60: =YEAR(I60) -> 2023 | P60: =IF(F60<500,"Low Price","High Price") -> High Price | Q60: =IF(J60>=AVERAGE(J:J),"Good","Bad") -> Good | R60: =IF(G60>10,"High Discount",IF(G60=0,"No Discount","Low Discont")) -> No Discount | S60: =IF(AND(H60="Yes",G60>10),"High Priority Review",IF(H60="Yes","Low Priority Review","No Review Needed")) -> Low Priority Review | T60: =LEFT(C60,2) -> Ea
A61: ORD0060 | B61: Blood Test Kit | C61: North | D61: Eva Brown | E61: 5 | F61: 1750 | G61: 20 | H61: No | I61: 45208 | J61: =E61*F61*(1-G61/100) -> 7000 | K61: =ROUND(J61*15%,2) -> 1050 | L61: =E61*F61 -> 8750 | M61: =DAY(I61) -> 9 | N61: =MONTH(I61) -> 10 | O61: =YEAR(I61) -> 2023 | P61: =IF(F61<500,"Low Price","High Price") -> High Price | Q61: =IF(J61>=AVERAGE(J:J),"Good","Bad") -> Bad | R61: =IF(G61>10,"High Discount",IF(G61=0,"No Discount","Low Discont")) -> High Discount | S61: =IF(AND(H61="Yes",G61>10),"High Priority Review",IF(H61="Yes","Low Priority Review","No Review Needed")) -> No Review Needed | T61: =LEFT(C61,2) -> No
A62: ORD0061 | B62: Thermometer | C62: North | D62: Eva Brown | E62: 9 | F62: 250 | G62: 0 | H62: No | I62: 44995 | J62: =E62*F62*(1-G62/100) -> 2250 | K62: =ROUND(J62*15%,2) -> 337.5 | L62: =E62*F62 -> 2250 | M62: =DAY(I62) -> 10 | N62: =MONTH(I62) -> 3 | O62: =YEAR(I62) -> 2023 | P62: =IF(F62<500,"Low Price","High Price") -> Low Price | Q62: =IF(J62>=AVERAGE(J:J),"Good","Bad") -> Bad | R62: =IF(G62>10,"High Discount",IF(G62=0,"No Discount","Low Discont")) -> No Discount | S62: =IF(AND(H62="Yes",G62>10),"High Priority Review",IF(H62="Yes","Low Priority Review","No Review Needed")) -> No Review Needed | T62: =LEFT(C62,2) -> No
A63: ORD0062 | B63: Insulin Pump | C63: South | D63: Henry Davis | E63: 29 | F63: 1000 | G63: 5 | H63: Yes | I63: 45056 | J63: =E63*F63*(1-G63/100) -> 27550 | K63: =ROUND(J63*15%,2) -> 4132.5 | L63: =E63*F63 -> 29000 | M63: =DAY(I63) -> 10 | N63: =MONTH(I63) -> 5 | O63: =YEAR(I63) -> 2023 | P63: =IF(F63<500,"Low Price","High Price") -> High Price | Q63: =IF(J63>=AVERAGE(J:J),"Good","Bad") -> Good | R63: =IF(G63>10,"High Discount",IF(G63=0,"No Discount","Low Discont")) -> Low Discont | S63: =IF(AND(H63="Yes",G63>10),"High Priority Review",IF(H63="Yes","Low Priority Review","No Review Needed")) -> Low Priority Review | T63: =LEFT(C63,2) -> So
A64: ORD0063 | B64: Thermometer | C64: South | D64: Bob Smith | E64: 12 | F64: 250 | G64: 15 | H64: Yes | I64: 45117 | J64: =E64*F64*(1-G64/100) -> 2550 | K64: =ROUND(J64*15%,2) -> 382.5 | L64: =E64*F64 -> 3000 | M64: =DAY(I64) -> 10 | N64: =MONTH(I64) -> 7 | O64: =YEAR(I64) -> 2023 | P64: =IF(F64<500,"Low Price","High Price") -> Low Price | Q64: =IF(J64>=AVERAGE(J:J),"Good","Bad") -> Bad | R64: =IF(G64>10,"High Discount",IF(G64=0,"No Discount","Low Discont")) -> High Discount | S64: =IF(AND(H64="Yes",G64>10),"High Priority Review",IF(H64="Yes","Low Priority Review","No Review Needed")) -> High Priority Review | T64: =LEFT(C64,2) -> So
A65: ORD0064 | B65: X-Ray Machine | C65: South | D65: Henry Davis | E65: 4 | F65: 5000 | G65: 10 | H65: Yes | I65: 45209 | J65: =E65*F65*(1-G65/100) -> 18000 | K65: =ROUND(J65*15%,2) -> 2700 | L65: =E65*F65 -> 20000 | M65: =DAY(I65) -> 10 | N65: =MONTH(I65) -> 10 | O65: =YEAR(I65) -> 2023 | P65: =IF(F65<500,"Low Price","High Price") -> High Price | Q65: =IF(J65>=AVERAGE(J:J),"Good","Bad") -> Bad | R65: =IF(G65>10,"High Discount",IF(G65=0,"No Discount","Low Discont")) -> Low Discont | S65: =IF(AND(H65="Yes",G65>10),"High Priority Review",IF(H65="Yes","Low Priority Review","No Review Needed")) -> Low Priority Review | T65: =LEFT(C65,2) -> So
A66: ORD0065 | B66: Blood Test Kit | C66: East | D66: Alice Johnson | E66: 49 | F66: 1750 | G66: 5 | H66: Yes | I66: 44937 | J66: =E66*F66*(1-G66/100) -> 81462.5 | K66: =ROUND(J66*15%,2) -> 12219.38 | L66: =E66*F66 -> 85750 | M66: =DAY(I66) -> 11 | N66: =MONTH(I66) -> 1 | O66: =YEAR(I66) -> 2023 | P66: =IF(F66<500,"Low Price","High Price") -> High Price | Q66: =IF(J66>=AVERAGE(J:J),"Good","Bad") -> Good | R66: =IF(G66>10,"High Discount",IF(G66=0,"No Discount","Low Discont")) -> Low Discont | S66: =IF(AND(H66="Yes",G66>10),"High Priority Review",IF(H66="Yes","Low Priority Review","No Review Needed")) -> Low Priority Review | T66: =LEFT(C66,2) -> Ea
A67: ORD0066 | B67: Syringe Pack | C67: South | D67: Bob Smith | E67: 32 | F67: 500 | G67: 15 | H67: Yes | I67: 44968 | J67: =E67*F67*(1-G67/100) -> 13600 | K67: =ROUND(J67*15%,2) -> 2040 | L67: =E67*F67 -> 16000 | M67: =DAY(I67) -> 11 | N67: =MONTH(I67) -> 2 | O67: =YEAR(I67) -> 2023 | P67: =IF(F67<500,"Low Price","High Price") -> High Price | Q67: =IF(J67>=AVERAGE(J:J),"Good","Bad") -> Bad | R67: =IF(G67>10,"High Discount",IF(G67=0,"No Discount","Low Discont")) -> High Discount | S67: =IF(AND(H67="Yes",G67>10),"High Priority Review",IF(H67="Yes","Low Priority Review","No Review Needed")) -> High Priority Review | T67: =LEFT(C67,2) -> So
... A76: ORD0075 | B76: Blood Test Kit | C76: West | D76: Frank Wilson | E76: 34 | F76: 1750 | G76: 10 | H76: Yes | I76: 45058 | J76: =E76*F76*(1-G76/100) -> 53550 | K76: =ROUND(J76*15%,2) -> 8032.5 | L76: =E76*F76 -> 59500 | M76: =DAY(I76) -> 12 | N76: =MONTH(I76) -> 5 | O76: =YEAR(I76) -> 2023 | P76: =IF(F76<500,"Low Price","High Price") -> High Price | Q76: =IF(J76>=AVERAGE(J:J),"Good","Bad") -> Good | R76: =IF(G76>10,"High Discount",IF(G76=0,"No Discount","Low Discont")) -> Low Discont | S76: =IF(AND(H76="Yes",G76>10),"High Priority Review",IF(H76="Yes","Low Priority Review","No Review Needed")) -> Low Priority Review | T76: =LEFT(C76,2) -> We
A77: ORD0076 | B77: Stethoscope | C77: South | D77: Henry Davis | E77: 5 | F77: 750 | H77: Yes | I77: 45058 | J77: =E77*F77*(1-G77/100) -> 3750 | K77: =ROUND(J77*15%,2) -> 562.5 | L77: =E77*F77 -> 3750 | M77: =DAY(I77) -> 12 | N77: =MONTH(I77) -> 5 | O77: =YEAR(I77) -> 2023 | P77: =IF(F77<500,"Low Price","High Price") -> High Price | Q77: =IF(J77>=AVERAGE(J:J),"Good","Bad") -> Bad | R77: =IF(G77>10,"High Discount",IF(G77=0,"No Discount","Low Discont")) -> No Discount | S77: =IF(AND(H77="Yes",G77>10),"High Priority Review",IF(H77="Yes","Low Priority Review","No Review Needed")) -> Low Priority Review | T77: =LEFT(C77,2) -> So
A78: ORD0077 | B78: Syringe Pack | C78: West | D78: Frank Wilson | E78: 44 | F78: 500 | G78: 20 | H78: No | I78: 45089 | J78: =E78*F78*(1-G78/100) -> 17600 | K78: =ROUND(J78*15%,2) -> 2640 | L78: =E78*F78 -> 22000 | M78: =DAY(I78) -> 12 | N78: =MONTH(I78) -> 6 | O78: =YEAR(I78) -> 2023 | P78: =IF(F78<500,"Low Price","High Price") -> High Price | Q78: =IF(J78>=AVERAGE(J:J),"Good","Bad") -> Bad | R78: =IF(G78>10,"High Discount",IF(G78=0,"No Discount","Low Discont")) -> High Discount | S78: =IF(AND(H78="Yes",G78>10),"High Priority Review",IF(H78="Yes","Low Priority Review","No Review Needed")) -> No Review Needed | T78: =LEFT(C78,2) -> We
A79: ORD0078 | B79: Blood Test Kit | C79: South | D79: Henry Davis | E79: 15 | F79: 1750 | G79: 0 | H79: No | I79: 45211 | J79: =E79*F79*(1-G79/100) -> 26250 | K79: =ROUND(J79*15%,2) -> 3937.5 | L79: =E79*F79 -> 26250 | M79: =DAY(I79) -> 12 | N79: =MONTH(I79) -> 10 | O79: =YEAR(I79) -> 2023 | P79: =IF(F79<500,"Low Price","High Price") -> High Price | Q79: =IF(J79>=AVERAGE(J:J),"Good","Bad") -> Good | R79: =IF(G79>10,"High Discount",IF(G79=0,"No Discount","Low Discont")) -> No Discount | S79: =IF(AND(H79="Yes",G79>10),"High Priority Review",IF(H79="Yes","Low Priority Review","No Review Needed")) -> No Review Needed | T79: =LEFT(C79,2) -> So
A80: ORD0079 | B80: Insulin Pump | C80: West | D80: David Miller | E80: 27 | F80: 1000 | G80: 15 | H80: Yes | I80: 45242 | J80: =E80*F80*(1-G80/100) -> 22950 | K80: =ROUND(J80*15%,2) -> 3442.5 | L80: =E80*F80 -> 27000 | M80: =DAY(I80) -> 12 | N80: =MONTH(I80) -> 11 | O80: =YEAR(I80) -> 2023 | P80: =IF(F80<500,"Low Price","High Price") -> High Price | Q80: =IF(J80>=AVERAGE(J:J),"Good","Bad") -> Good | R80: =IF(G80>10,"High Discount",IF(G80=0,"No Discount","Low Discont")) -> High Discount | S80: =IF(AND(H80="Yes",G80>10),"High Priority Review",IF(H80="Yes","Low Priority Review","No Review Needed")) -> High Priority Review | T80: =LEFT(C80,2) -> We
A81: ORD0080 | B81: Ultrasound Device | C81: North | D81: Eva Brown | E81: 3 | F81: 2000 | G81: 20 | H81: Yes | I81: 44970 | J81: =E81*F81*(1-G81/100) -> 4800 | K81: =ROUND(J81*15%,2) -> 720 | L81: =E81*F81 -> 6000 | M81: =DAY(I81) -> 13 | N81: =MONTH(I81) -> 2 | O81: =YEAR(I81) -> 2023 | P81: =IF(F81<500,"Low Price","High Price") -> High Price | Q81: =IF(J81>=AVERAGE(J:J),"Good","Bad") -> Bad | R81: =IF(G81>10,"High Discount",IF(G81=0,"No Discount","Low Discont")) -> High Discount | S81: =IF(AND(H81="Yes",G81>10),"High Priority Review",IF(H81="Yes","Low Priority Review","No Review Needed")) -> High Priority Review | T81: =LEFT(C81,2) -> No
A82: ORD0081 | B82: Syringe Pack | C82: North | D82: Catherine Lee | E82: 48 | F82: 500 | G82: 15 | H82: No | I82: 45059 | J82: =E82*F82*(1-G82/100) -> 20400 | K82: =ROUND(J82*15%,2) -> 3060 | L82: =E82*F82 -> 24000 | M82: =DAY(I82) -> 13 | N82: =MONTH(I82) -> 5 | O82: =YEAR(I82) -> 2023 | P82: =IF(F82<500,"Low Price","High Price") -> High Price | Q82: =IF(J82>=AVERAGE(J:J),"Good","Bad") -> Good | R82: =IF(G82>10,"High Discount",IF(G82=0,"No Discount","Low Discont")) -> High Discount | S82: =IF(AND(H82="Yes",G82>10),"High Priority Review",IF(H82="Yes","Low Priority Review","No Review Needed")) -> No Review Needed | T82: =LEFT(C82,2) -> No
A83: ORD0082 | B83: PPE Kit | C83: West | D83: Frank Wilson | E83: 13 | F83: 3000 | G83: 5 | H83: No | I83: 45059 | J83: =E83*F83*(1-G83/100) -> 37050 | K83: =ROUND(J83*15%,2) -> 5557.5 | L83: =E83*F83 -> 39000 | M83: =DAY(I83) -> 13 | N83: =MONTH(I83) -> 5 | O83: =YEAR(I83) -> 2023 | P83: =IF(F83<500,"Low Price","High Price") -> High Price | Q83: =IF(J83>=AVERAGE(J:J),"Good","Bad") -> Good | R83: =IF(G83>10,"High Discount",IF(G83=0,"No Discount","Low Discont")) -> Low Discont | S83: =IF(AND(H83="Yes",G83>10),"High Priority Review",IF(H83="Yes","Low Priority Review","No Review Needed")) -> No Review Needed | T83: =LEFT(C83,2) -> We
A84: ORD0083 | B84: Ultrasound Device | C84: East | D84: Grace Kim | E84: 1 | F84: 2000 | G84: 5 | H84: Yes | I84: 45090 | J84: =E84*F84*(1-G84/100) -> 1900 | K84: =ROUND(J84*15%,2) -> 285 | L84: =E84*F84 -> 2000 | M84: =DAY(I84) -> 13 | N84: =MONTH(I84) -> 6 | O84: =YEAR(I84) -> 2023 | P84: =IF(F84<500,"Low Price","High Price") -> High Price | Q84: =IF(J84>=AVERAGE(J:J),"Good","Bad") -> Bad | R84: =IF(G84>10,"High Discount",IF(G84=0,"No Discount","Low Discont")) -> Low Discont | S84: =IF(AND(H84="Yes",G84>10),"High Priority Review",IF(H84="Yes","Low Priority Review","No Review Needed")) -> Low Priority Review | T84: =LEFT(C84,2) -> Ea
A85: ORD0084 | B85: Ultrasound Device | C85: West | D85: Frank Wilson | E85: 1 | F85: 2000 | G85: 5 | H85: Yes | I85: 44940 | J85: =E85*F85*(1-G85/100) -> 1900 | K85: =ROUND(J85*15%,2) -> 285 | L85: =E85*F85 -> 2000 | M85: =DAY(I85) -> 14 | N85: =MONTH(I85) -> 1 | O85: =YEAR(I85) -> 2023 | P85: =IF(F85<500,"Low Price","High Price") -> High Price | Q85: =IF(J85>=AVERAGE(J:J),"Good","Bad") -> Bad | R85: =IF(G85>10,"High Discount",IF(G85=0,"No Discount","Low Discont")) -> Low Discont | S85: =IF(AND(H85="Yes",G85>10),"High Priority Review",IF(H85="Yes","Low Priority Review","No Review Needed")) -> Low Priority Review | T85: =LEFT(C85,2) -> We
A86: ORD0085 | B86: PPE Kit | C86: North | D86: Catherine Lee | E86: 5 | F86: 3000 | G86: 15 | H86: Yes | I86: 44999 | J86: =E86*F86*(1-G86/100) -> 12750 | K86: =ROUND(J86*15%,2) -> 1912.5 | L86: =E86*F86 -> 15000 | M86: =DAY(I86) -> 14 | N86: =MONTH(I86) -> 3 | O86: =YEAR(I86) -> 2023 | P86: =IF(F86<500,"Low Price","High Price") -> High Price | Q86: =IF(J86>=AVERAGE(J:J),"Good","Bad") -> Bad | R86: =IF(G86>10,"High Discount",IF(G86=0,"No Discount","Low Discont")) -> High Discount | S86: =IF(AND(H86="Yes",G86>10),"High Priority Review",IF(H86="Yes","Low Priority Review","No Review Needed")) -> High Priority Review | T86: =LEFT(C86,2) -> No
A87: ORD0086 | B87: Syringe Pack | C87: South | D87: Bob Smith | E87: 31 | F87: 500 | G87: 15 | H87: No | I87: 45091 | J87: =E87*F87*(1-G87/100) -> 13175 | K87: =ROUND(J87*15%,2) -> 1976.25 | L87: =E87*F87 -> 15500 | M87: =DAY(I87) -> 14 | N87: =MONTH(I87) -> 6 | O87: =YEAR(I87) -> 2023 | P87: =IF(F87<500,"Low Price","High Price") -> High Price | Q87: =IF(J87>=AVERAGE(J:J),"Good","Bad") -> Bad | R87: =IF(G87>10,"High Discount",IF(G87=0,"No Discount","Low Discont")) -> High Discount | S87: =IF(AND(H87="Yes",G87>10),"High Priority Review",IF(H87="Yes","Low Priority Review","No Review Needed")) -> No Review Needed | T87: =LEFT(C87,2) -> So
A88: ORD0087 | B88: Insulin Pump | C88: West | D88: Frank Wilson | E88: 14 | F88: 1000 | G88: 10 | H88: No | I88: 45121 | J88: =E88*F88*(1-G88/100) -> 12600 | K88: =ROUND(J88*15%,2) -> 1890 | L88: =E88*F88 -> 14000 | M88: =DAY(I88) -> 14 | N88: =MONTH(I88) -> 7 | O88: =YEAR(I88) -> 2023 | P88: =IF(F88<500,"Low Price","High Price") -> High Price | Q88: =IF(J88>=AVERAGE(J:J),"Good","Bad") -> Bad | R88: =IF(G88>10,"High Discount",IF(G88=0,"No Discount","Low Discont")) -> Low Discont | S88: =IF(AND(H88="Yes",G88>10),"High Priority Review",IF(H88="Yes","Low Priority Review","No Review Needed")) -> No Review Needed | T88: =LEFT(C88,2) -> We
A89: ORD0088 | B89: Blood Test Kit | C89: North | D89: Catherine Lee | E89: 41 | F89: 1750 | G89: 0 | H89: No | I89: 45152 | J89: =E89*F89*(1-G89/100) -> 71750 | K89: =ROUND(J89*15%,2) -> 10762.5 | L89: =E89*F89 -> 71750 | M89: =DAY(I89) -> 14 | N89: =MONTH(I89) -> 8 | O89: =YEAR(I89) -> 2023 | P89: =IF(F89<500,"Low Price","High Price") -> High Price | Q89: =IF(J89>=AVERAGE(J:J),"Good","Bad") -> Good | R89: =IF(G89>10,"High Discount",IF(G89=0,"No Discount","Low Discont")) -> No Discount | S89: =IF(AND(H89="Yes",G89>10),"High Priority Review",IF(H89="Yes","Low Priority Review","No Review Needed")) -> No Review Needed | T89: =LEFT(C89,2) -> No
... A92: ORD0091 | B92: Stethoscope | C92: West | D92: Frank Wilson | E92: 11 | F92: 750 | G92: 15 | H92: No | I92: 45274 | J92: =E92*F92*(1-G92/100) -> 7012.5 | K92: =ROUND(J92*15%,2) -> 1051.88 | L92: =E92*F92 -> 8250 | M92: =DAY(I92) -> 14 | N92: =MONTH(I92) -> 12 | O92: =YEAR(I92) -> 2023 | P92: =IF(F92<500,"Low Price","High Price") -> High Price | Q92: =IF(J92>=AVERAGE(J:J),"Good","Bad") -> Bad | R92: =IF(G92>10,"High Discount",IF(G92=0,"No Discount","Low Discont")) -> High Discount | S92: =IF(AND(H92="Yes",G92>10),"High Priority Review",IF(H92="Yes","Low Priority Review","No Review Needed")) -> No Review Needed | T92: =LEFT(C92,2) -> We
A93: ORD0092 | B93: X-Ray Machine | C93: East | E93: 7 | F93: 5000 | G93: 20 | H93: Yes | I93: 45000 | J93: =E93*F93*(1-G93/100) -> 28000 | K93: =ROUND(J93*15%,2) -> 4200 | L93: =E93*F93 -> 35000 | M93: =DAY(I93) -> 15 | N93: =MONTH(I93) -> 3 | O93: =YEAR(I93) -> 2023 | P93: =IF(F93<500,"Low Price","High Price") -> High Price | Q93: =IF(J93>=AVERAGE(J:J),"Good","Bad") -> Good | R93: =IF(G93>10,"High Discount",IF(G93=0,"No Discount","Low Discont")) -> High Discount | S93: =IF(AND(H93="Yes",G93>10),"High Priority Review",IF(H93="Yes","Low Priority Review","No Review Needed")) -> High Priority Review | T93: =LEFT(C93,2) -> Ea
A94: ORD0093 | B94: Insulin Pump | C94: West | D94: David Miller | E94: 26 | F94: 1000 | G94: 0 | H94: Yes | I94: 45031 | J94: =E94*F94*(1-G94/100) -> 26000 | K94: =ROUND(J94*15%,2) -> 3900 | L94: =E94*F94 -> 26000 | M94: =DAY(I94) -> 15 | N94: =MONTH(I94) -> 4 | O94: =YEAR(I94) -> 2023 | P94: =IF(F94<500,"Low Price","High Price") -> High Price | Q94: =IF(J94>=AVERAGE(J:J),"Good","Bad") -> Good | R94: =IF(G94>10,"High Discount",IF(G94=0,"No Discount","Low Discont")) -> No Discount | S94: =IF(AND(H94="Yes",G94>10),"High Priority Review",IF(H94="Yes","Low Priority Review","No Review Needed")) -> Low Priority Review | T94: =LEFT(C94,2) -> We
A95: ORD0094 | B95: Stethoscope | C95: South | D95: Henry Davis | E95: 13 | F95: 750 | G95: 20 | H95: No | I95: 45092 | J95: =E95*F95*(1-G95/100) -> 7800 | K95: =ROUND(J95*15%,2) -> 1170 | L95: =E95*F95 -> 9750 | M95: =DAY(I95) -> 15 | N95: =MONTH(I95) -> 6 | O95: =YEAR(I95) -> 2023 | P95: =IF(F95<500,"Low Price","High Price") -> High Price | Q95: =IF(J95>=AVERAGE(J:J),"Good","Bad") -> Bad | R95: =IF(G95>10,"High Discount",IF(G95=0,"No Discount","Low Discont")) -> High Discount | S95: =IF(AND(H95="Yes",G95>10),"High Priority Review",IF(H95="Yes","Low Priority Review","No Review Needed")) -> No Review Needed | T95: =LEFT(C95,2) -> So
A96: ORD0095 | B96: Ultrasound Device | C96: South | D96: Bob Smith | E96: 1 | F96: 2000 | G96: 20 | H96: No | I96: 45122 | J96: =E96*F96*(1-G96/100) -> 1600 | K96: =ROUND(J96*15%,2) -> 240 | L96: =E96*F96 -> 2000 | M96: =DAY(I96) -> 15 | N96: =MONTH(I96) -> 7 | O96: =YEAR(I96) -> 2023 | P96: =IF(F96<500,"Low Price","High Price") -> High Price | Q96: =IF(J96>=AVERAGE(J:J),"Good","Bad") -> Bad | R96: =IF(G96>10,"High Discount",IF(G96=0,"No Discount","Low Discont")) -> High Discount | S96: =IF(AND(H96="Yes",G96>10),"High Priority Review",IF(H96="Yes","Low Priority Review","No Review Needed")) -> No Review Needed | T96: =LEFT(C96,2) -> So
A97: ORD0096 | B97: Blood Test Kit | C97: South | D97: Henry Davis | E97: 9 | F97: 1750 | G97: 15 | H97: No | I97: 45153 | J97: =E97*F97*(1-G97/100) -> 13387.5 | K97: =ROUND(J97*15%,2) -> 2008.13 | L97: =E97*F97 -> 15750 | M97: =DAY(I97) -> 15 | N97: =MONTH(I97) -> 8 | O97: =YEAR(I97) -> 2023 | P97: =IF(F97<500,"Low Price","High Price") -> High Price | Q97: =IF(J97>=AVERAGE(J:J),"Good","Bad") -> Bad | R97: =IF(G97>10,"High Discount",IF(G97=0,"No Discount","Low Discont")) -> High Discount | S97: =IF(AND(H97="Yes",G97>10),"High Priority Review",IF(H97="Yes","Low Priority Review","No Review Needed")) -> No Review Needed | T97: =LEFT(C97,2) -> So
A98: ORD0097 | B98: PPE Kit | C98: North | D98: Eva Brown | E98: 21 | F98: 3000 | G98: 5 | H98: Yes | I98: 45153 | J98: =E98*F98*(1-G98/100) -> 59850 | K98: =ROUND(J98*15%,2) -> 8977.5 | L98: =E98*F98 -> 63000 | M98: =DAY(I98) -> 15 | N98: =MONTH(I98) -> 8 | O98: =YEAR(I98) -> 2023 | P98: =IF(F98<500,"Low Price","High Price") -> High Price | Q98: =IF(J98>=AVERAGE(J:J),"Good","Bad") -> Good | R98: =IF(G98>10,"High Discount",IF(G98=0,"No Discount","Low Discont")) -> Low Discont | S98: =IF(AND(H98="Yes",G98>10),"High Priority Review",IF(H98="Yes","Low Priority Review","No Review Needed")) -> Low Priority Review | T98: =LEFT(C98,2) -> No
A99: ORD0098 | B99: Thermometer | C99: West | D99: Frank Wilson | E99: 7 | F99: 250 | G99: 0 | H99: No | I99: 45184 | J99: =E99*F99*(1-G99/100) -> 1750 | K99: =ROUND(J99*15%,2) -> 262.5 | L99: =E99*F99 -> 1750 | M99: =DAY(I99) -> 15 | N99: =MONTH(I99) -> 9 | O99: =YEAR(I99) -> 2023 | P99: =IF(F99<500,"Low Price","High Price") -> Low Price | Q99: =IF(J99>=AVERAGE(J:J),"Good","Bad") -> Bad | R99: =IF(G99>10,"High Discount",IF(G99=0,"No Discount","Low Discont")) -> No Discount | S99: =IF(AND(H99="Yes",G99>10),"High Priority Review",IF(H99="Yes","Low Priority Review","No Review Needed")) -> No Review Needed | T99: =LEFT(C99,2) -> We
A100: ORD0099 | B100: Blood Test Kit | C100: West | D100: Frank Wilson | E100: 2 | F100: 1750 | H100: No | I100: 45184 | J100: =E100*F100*(1-G100/100) -> 3500 | K100: =ROUND(J100*15%,2) -> 525 | L100: =E100*F100 -> 3500 | M100: =DAY(I100) -> 15 | N100: =MONTH(I100) -> 9 | O100: =YEAR(I100) -> 2023 | P100: =IF(F100<500,"Low Price","High Price") -> High Price | Q100: =IF(J100>=AVERAGE(J:J),"Good","Bad") -> Bad | R100: =IF(G100>10,"High Discount",IF(G100=0,"No Discount","Low Discont")) -> No Discount | S100: =IF(AND(H100="Yes",G100>10),"High Priority Review",IF(H100="Yes","Low Priority Review","No Review Needed")) -> No Review Needed | T100: =LEFT(C100,2) -> We
A101: ORD0100 | B101: Syringe Pack | C101: South | D101: Henry Davis | E101: 27 | F101: 500 | G101: 5 | H101: No | I101: 45245 | J101: =E101*F101*(1-G101/100) -> 12825 | K101: =ROUND(J101*15%,2) -> 1923.75 | L101: =E101*F101 -> 13500 | M101: =DAY(I101) -> 15 | N101: =MONTH(I101) -> 11 | O101: =YEAR(I101) -> 2023 | P101: =IF(F101<500,"Low Price","High Price") -> High Price | Q101: =IF(J101>=AVERAGE(J:J),"Good","Bad") -> Bad | R101: =IF(G101>10,"High Discount",IF(G101=0,"No Discount","Low Discont")) -> Low Discont | S101: =IF(AND(H101="Yes",G101>10),"High Priority Review",IF(H101="Yes","Low Priority Review","No Review Needed")) -> No Review Needed | T101: =LEFT(C101,2) -> So
A102: ORD0101 | B102: X-Ray Machine | C102: South | D102: Henry Davis | E102: 10 | F102: 5000 | G102: 20 | H102: No | I102: 45275 | J102: =E102*F102*(1-G102/100) -> 40000 | K102: =ROUND(J102*15%,2) -> 6000 | L102: =E102*F102 -> 50000 | M102: =DAY(I102) -> 15 | N102: =MONTH(I102) -> 12 | O102: =YEAR(I102) -> 2023 | P102: =IF(F102<500,"Low Price","High Price") -> High Price | Q102: =IF(J102>=AVERAGE(J:J),"Good","Bad") -> Good | R102: =IF(G102>10,"High Discount",IF(G102=0,"No Discount","Low Discont")) -> High Discount | S102: =IF(AND(H102="Yes",G102>10),"High Priority Review",IF(H102="Yes","Low Priority Review","No Review Needed")) -> No Review Needed | T102: =LEFT(C102,2) -> So
A103: ORD0102 | B103: Thermometer | C103: South | D103: Bob Smith | E103: 9 | F103: 250 | G103: 10 | H103: Yes | I103: 44973 | J103: =E103*F103*(1-G103/100) -> 2025 | K103: =ROUND(J103*15%,2) -> 303.75 | L103: =E103*F103 -> 2250 | M103: =DAY(I103) -> 16 | N103: =MONTH(I103) -> 2 | O103: =YEAR(I103) -> 2023 | P103: =IF(F103<500,"Low Price","High Price") -> Low Price | Q103: =IF(J103>=AVERAGE(J:J),"Good","Bad") -> Bad | R103: =IF(G103>10,"High Discount",IF(G103=0,"No Discount","Low Discont")) -> Low Discont | S103: =IF(AND(H103="Yes",G103>10),"High Priority Review",IF(H103="Yes","Low Priority Review","No Review Needed")) -> Low Priority Review | T103: =LEFT(C103,2) -> So
A104: ORD0103 | B104: X-Ray Machine | C104: North | D104: Eva Brown | E104: 4 | F104: 5000 | G104: 5 | H104: No | I104: 44973 | J104: =E104*F104*(1-G104/100) -> 19000 | K104: =ROUND(J104*15%,2) -> 2850 | L104: =E104*F104 -> 20000 | M104: =DAY(I104) -> 16 | N104: =MONTH(I104) -> 2 | O104: =YEAR(I104) -> 2023 | P104: =IF(F104<500,"Low Price","High Price") -> High Price | Q104: =IF(J104>=AVERAGE(J:J),"Good","Bad") -> Bad | R104: =IF(G104>10,"High Discount",IF(G104=0,"No Discount","Low Discont")) -> Low Discont | S104: =IF(AND(H104="Yes",G104>10),"High Priority Review",IF(H104="Yes","Low Priority Review","No Review Needed")) -> No Review Needed | T104: =LEFT(C104,2) -> No
A105: ORD0104 | B105: Thermometer | C105: North | D105: Eva Brown | E105: 16 | F105: 250 | G105: 0 | H105: No | I105: 45185 | J105: =E105*F105*(1-G105/100) -> 4000 | K105: =ROUND(J105*15%,2) -> 600 | L105: =E105*F105 -> 4000 | M105: =DAY(I105) -> 16 | N105: =MONTH(I105) -> 9 | O105: =YEAR(I105) -> 2023 | P105: =IF(F105<500,"Low Price","High Price") -> Low Price | Q105: =IF(J105>=AVERAGE(J:J),"Good","Bad") -> Bad | R105: =IF(G105>10,"High Discount",IF(G105=0,"No Discount","Low Discont")) -> No Discount | S105: =IF(AND(H105="Yes",G105>10),"High Priority Review",IF(H105="Yes","Low Priority Review","No Review Needed")) -> No Review Needed | T105: =LEFT(C105,2) -> No
A106: ORD0105 | B106: Stethoscope | C106: North | D106: Catherine Lee | E106: 10 | F106: 750 | G106: 10 | H106: No | I106: 45246 | J106: =E106*F106*(1-G106/100) -> 6750 | K106: =ROUND(J106*15%,2) -> 1012.5 | L106: =E106*F106 -> 7500 | M106: =DAY(I106) -> 16 | N106: =MONTH(I106) -> 11 | O106: =YEAR(I106) -> 2023 | P106: =IF(F106<500,"Low Price","High Price") -> High Price | Q106: =IF(J106>=AVERAGE(J:J),"Good","Bad") -> Bad | R106: =IF(G106>10,"High Discount",IF(G106=0,"No Discount","Low Discont")) -> Low Discont | S106: =IF(AND(H106="Yes",G106>10),"High Priority Review",IF(H106="Yes","Low Priority Review","No Review Needed")) -> No Review Needed | T106: =LEFT(C106,2) -> No
A107: ORD0106 | B107: Stethoscope | C107: South | D107: Bob Smith | E107: 14 | F107: 750 | G107: 15 | H107: No | I107: 44943 | J107: =E107*F107*(1-G107/100) -> 8925 | K107: =ROUND(J107*15%,2) -> 1338.75 | L107: =E107*F107 -> 10500 | M107: =DAY(I107) -> 17 | N107: =MONTH(I107) -> 1 | O107: =YEAR(I107) -> 2023 | P107: =IF(F107<500,"Low Price","High Price") -> High Price | Q107: =IF(J107>=AVERAGE(J:J),"Good","Bad") -> Bad | R107: =IF(G107>10,"High Discount",IF(G107=0,"No Discount","Low Discont")) -> High Discount | S107: =IF(AND(H107="Yes",G107>10),"High Priority Review",IF(H107="Yes","Low Priority Review","No Review Needed")) -> No Review Needed | T107: =LEFT(C107,2) -> So
A108: ORD0107 | B108: Blood Test Kit | C108: West | D108: David Miller | E108: 38 | F108: 1750 | G108: 5 | H108: No | I108: 45002 | J108: =E108*F108*(1-G108/100) -> 63175 | K108: =ROUND(J108*15%,2) -> 9476.25 | L108: =E108*F108 -> 66500 | M108: =DAY(I108) -> 17 | N108: =MONTH(I108) -> 3 | O108: =YEAR(I108) -> 2023 | P108: =IF(F108<500,"Low Price","High Price") -> High Price | Q108: =IF(J108>=AVERAGE(J:J),"Good","Bad") -> Good | R108: =IF(G108>10,"High Discount",IF(G108=0,"No Discount","Low Discont")) -> Low Discont | S108: =IF(AND(H108="Yes",G108>10),"High Priority Review",IF(H108="Yes","Low Priority Review","No Review Needed")) -> No Review Needed | T108: =LEFT(C108,2) -> We
A109: ORD0108 | B109: Insulin Pump | C109: South | D109: Bob Smith | E109: 31 | F109: 1000 | G109: 10 | H109: No | I109: 45155 | J109: =E109*F109*(1-G109/100) -> 27900 | K109: =ROUND(J109*15%,2) -> 4185 | L109: =E109*F109 -> 31000 | M109: =DAY(I109) -> 17 | N109: =MONTH(I109) -> 8 | O109: =YEAR(I109) -> 2023 | P109: =IF(F109<500,"Low Price","High Price") -> High Price | Q109: =IF(J109>=AVERAGE(J:J),"Good","Bad") -> Good | R109: =IF(G109>10,"High Discount",IF(G109=0,"No Discount","Low Discont")) -> Low Discont | S109: =IF(AND(H109="Yes",G109>10),"High Priority Review",IF(H109="Yes","Low Priority Review","No Review Needed")) -> No Review Needed | T109: =LEFT(C109,2) -> So
A110: ORD0109 | B110: Stethoscope | C110: North | D110: Eva Brown | E110: 14 | F110: 750 | G110: 15 | H110: No | I110: 45186 | J110: =E110*F110*(1-G110/100) -> 8925 | K110: =ROUND(J110*15%,2) -> 1338.75 | L110: =E110*F110 -> 10500 | M110: =DAY(I110) -> 17 | N110: =MONTH(I110) -> 9 | O110: =YEAR(I110) -> 2023 | P110: =IF(F110<500,"Low Price","High Price") -> High Price | Q110: =IF(J110>=AVERAGE(J:J),"Good","Bad") -> Bad | R110: =IF(G110>10,"High Discount",IF(G110=0,"No Discount","Low Discont")) -> High Discount | S110: =IF(AND(H110="Yes",G110>10),"High Priority Review",IF(H110="Yes","Low Priority Review","No Review Needed")) -> No Review Needed | T110: =LEFT(C110,2) -> No
A111: ORD0110 | B111: X-Ray Machine | C111: South | D111: Bob Smith | E111: 9 | F111: 5000 | G111: 10 | H111: Yes | I111: 45216 | J111: =E111*F111*(1-G111/100) -> 40500 | K111: =ROUND(J111*15%,2) -> 6075 | L111: =E111*F111 -> 45000 | M111: =DAY(I111) -> 17 | N111: =MONTH(I111) -> 10 | O111: =YEAR(I111) -> 2023 | P111: =IF(F111<500,"Low Price","High Price") -> High Price | Q111: =IF(J111>=AVERAGE(J:J),"Good","Bad") -> Good | R111: =IF(G111>10,"High Discount",IF(G111=0,"No Discount","Low Discont")) -> Low Discont | S111: =IF(AND(H111="Yes",G111>10),"High Priority Review",IF(H111="Yes","Low Priority Review","No Review Needed")) -> Low Priority Review | T111: =LEFT(C111,2) -> So
A112: ORD0111 | B112: Insulin Pump | C112: East | D112: Alice Johnson | E112: 43 | F112: 1000 | G112: 10 | H112: Yes | I112: 45216 | J112: =E112*F112*(1-G112/100) -> 38700 | K112: =ROUND(J112*15%,2) -> 5805 | L112: =E112*F112 -> 43000 | M112: =DAY(I112) -> 17 | N112: =MONTH(I112) -> 10 | O112: =YEAR(I112) -> 2023 | P112: =IF(F112<500,"Low Price","High Price") -> High Price | Q112: =IF(J112>=AVERAGE(J:J),"Good","Bad") -> Good | R112: =IF(G112>10,"High Discount",IF(G112=0,"No Discount","Low Discont")) -> Low Discont | S112: =IF(AND(H112="Yes",G112>10),"High Priority Review",IF(H112="Yes","Low Priority Review","No Review Needed")) -> Low Priority Review | T112: =LEFT(C112,2) -> Ea
... A171: ORD0170 | B171: X-Ray Machine | C171: West | D171: Frank Wilson | E171: 5 | F171: 5000 | G171: 5 | H171: No | I171: 45042 | J171: =E171*F171*(1-G171/100) -> 23750 | K171: =ROUND(J171*15%,2) -> 3562.5 | L171: =E171*F171 -> 25000 | M171: =DAY(I171) -> 26 | N171: =MONTH(I171) -> 4 | O171: =YEAR(I171) -> 2023 | P171: =IF(F171<500,"Low Price","High Price") -> High Price | Q171: =IF(J171>=AVERAGE(J:J),"Good","Bad") -> Good | R171: =IF(G171>10,"High Discount",IF(G171=0,"No Discount","Low Discont")) -> Low Discont | S171: =IF(AND(H171="Yes",G171>10),"High Priority Review",IF(H171="Yes","Low Priority Review","No Review Needed")) -> No Review Needed | T171: =LEFT(C171,2) -> We
A172: ORD0171 | B172: Thermometer | C172: West | D172: Frank Wilson | E172: 22 | F172: 250 | H172: Yes | I172: 45042 | J172: =E172*F172*(1-G172/100) -> 5500 | K172: =ROUND(J172*15%,2) -> 825 | L172: =E172*F172 -> 5500 | M172: =DAY(I172) -> 26 | N172: =MONTH(I172) -> 4 | O172: =YEAR(I172) -> 2023 | P172: =IF(F172<500,"Low Price","High Price") -> Low Price | Q172: =IF(J172>=AVERAGE(J:J),"Good","Bad") -> Bad | R172: =IF(G172>10,"High Discount",IF(G172=0,"No Discount","Low Discont")) -> No Discount | S172: =IF(AND(H172="Yes",G172>10),"High Priority Review",IF(H172="Yes","Low Priority Review","No Review Needed")) -> Low Priority Review | T172: =LEFT(C172,2) -> We
A173: ORD0172 | B173: PPE Kit | C173: South | D173: Bob Smith | E173: 6 | F173: 3000 | G173: 20 | H173: No | I173: 45072 | J173: =E173*F173*(1-G173/100) -> 14400 | K173: =ROUND(J173*15%,2) -> 2160 | L173: =E173*F173 -> 18000 | M173: =DAY(I173) -> 26 | N173: =MONTH(I173) -> 5 | O173: =YEAR(I173) -> 2023 | P173: =IF(F173<500,"Low Price","High Price") -> High Price | Q173: =IF(J173>=AVERAGE(J:J),"Good","Bad") -> Bad | R173: =IF(G173>10,"High Discount",IF(G173=0,"No Discount","Low Discont")) -> High Discount | S173: =IF(AND(H173="Yes",G173>10),"High Priority Review",IF(H173="Yes","Low Priority Review","No Review Needed")) -> No Review Needed | T173: =LEFT(C173,2) -> So
A174: ORD0173 | B174: PPE Kit | C174: West | D174: Frank Wilson | E174: 27 | F174: 3000 | G174: 20 | H174: Yes | I174: 45072 | J174: =E174*F174*(1-G174/100) -> 64800 | K174: =ROUND(J174*15%,2) -> 9720 | L174: =E174*F174 -> 81000 | M174: =DAY(I174) -> 26 | N174: =MONTH(I174) -> 5 | O174: =YEAR(I174) -> 2023 | P174: =IF(F174<500,"Low Price","High Price") -> High Price | Q174: =IF(J174>=AVERAGE(J:J),"Good","Bad") -> Good | R174: =IF(G174>10,"High Discount",IF(G174=0,"No Discount","Low Discont")) -> High Discount | S174: =IF(AND(H174="Yes",G174>10),"High Priority Review",IF(H174="Yes","Low Priority Review","No Review Needed")) -> High Priority Review | T174: =LEFT(C174,2) -> We
A175: ORD0174 | B175: Syringe Pack | C175: South | D175: Henry Davis | E175: 27 | F175: 500 | G175: 5 | H175: Yes | I175: 45103 | J175: =E175*F175*(1-G175/100) -> 12825 | K175: =ROUND(J175*15%,2) -> 1923.75 | L175: =E175*F175 -> 13500 | M175: =DAY(I175) -> 26 | N175: =MONTH(I175) -> 6 | O175: =YEAR(I175) -> 2023 | P175: =IF(F175<500,"Low Price","High Price") -> High Price | Q175: =IF(J175>=AVERAGE(J:J),"Good","Bad") -> Bad | R175: =IF(G175>10,"High Discount",IF(G175=0,"No Discount","Low Discont")) -> Low Discont | S175: =IF(AND(H175="Yes",G175>10),"High Priority Review",IF(H175="Yes","Low Priority Review","No Review Needed")) -> Low Priority Review | T175: =LEFT(C175,2) -> So
A176: ORD0175 | B176: Ultrasound Device | C176: East | D176: Grace Kim | E176: 2 | F176: 2000 | G176: 15 | H176: No | I176: 45195 | J176: =E176*F176*(1-G176/100) -> 3400 | K176: =ROUND(J176*15%,2) -> 510 | L176: =E176*F176 -> 4000 | M176: =DAY(I176) -> 26 | N176: =MONTH(I176) -> 9 | O176: =YEAR(I176) -> 2023 | P176: =IF(F176<500,"Low Price","High Price") -> High Price | Q176: =IF(J176>=AVERAGE(J:J),"Good","Bad") -> Bad | R176: =IF(G176>10,"High Discount",IF(G176=0,"No Discount","Low Discont")) -> High Discount | S176: =IF(AND(H176="Yes",G176>10),"High Priority Review",IF(H176="Yes","Low Priority Review","No Review Needed")) -> No Review Needed | T176: =LEFT(C176,2) -> Ea
A177: ORD0176 | B177: Ultrasound Device | C177: North | D177: Catherine Lee | E177: 1 | F177: 2000 | G177: 15 | H177: No | I177: 45195 | J177: =E177*F177*(1-G177/100) -> 1700 | K177: =ROUND(J177*15%,2) -> 255 | L177: =E177*F177 -> 2000 | M177: =DAY(I177) -> 26 | N177: =MONTH(I177) -> 9 | O177: =YEAR(I177) -> 2023 | P177: =IF(F177<500,"Low Price","High Price") -> High Price | Q177: =IF(J177>=AVERAGE(J:J),"Good","Bad") -> Bad | R177: =IF(G177>10,"High Discount",IF(G177=0,"No Discount","Low Discont")) -> High Discount | S177: =IF(AND(H177="Yes",G177>10),"High Priority Review",IF(H177="Yes","Low Priority Review","No Review Needed")) -> No Review Needed | T177: =LEFT(C177,2) -> No
A178: ORD0177 | B178: Ultrasound Device | C178: West | D178: Frank Wilson | E178: 3 | F178: 2000 | G178: 20 | H178: Yes | I178: 44953 | J178: =E178*F178*(1-G178/100) -> 4800 | K178: =ROUND(J178*15%,2) -> 720 | L178: =E178*F178 -> 6000 | M178: =DAY(I178) -> 27 | N178: =MONTH(I178) -> 1 | O178: =YEAR(I178) -> 2023 | P178: =IF(F178<500,"Low Price","High Price") -> High Price | Q178: =IF(J178>=AVERAGE(J:J),"Good","Bad") -> Bad | R178: =IF(G178>10,"High Discount",IF(G178=0,"No Discount","Low Discont")) -> High Discount | S178: =IF(AND(H178="Yes",G178>10),"High Priority Review",IF(H178="Yes","Low Priority Review","No Review Needed")) -> High Priority Review | T178: =LEFT(C178,2) -> We
A179: ORD0178 | B179: Thermometer | C179: North | D179: Eva Brown | E179: 21 | F179: 250 | G179: 5 | H179: No | I179: 45043 | J179: =E179*F179*(1-G179/100) -> 4987.5 | K179: =ROUND(J179*15%,2) -> 748.13 | L179: =E179*F179 -> 5250 | M179: =DAY(I179) -> 27 | N179: =MONTH(I179) -> 4 | O179: =YEAR(I179) -> 2023 | P179: =IF(F179<500,"Low Price","High Price") -> Low Price | Q179: =IF(J179>=AVERAGE(J:J),"Good","Bad") -> Bad | R179: =IF(G179>10,"High Discount",IF(G179=0,"No Discount","Low Discont")) -> Low Discont | S179: =IF(AND(H179="Yes",G179>10),"High Priority Review",IF(H179="Yes","Low Priority Review","No Review Needed")) -> No Review Needed | T179: =LEFT(C179,2) -> No
A180: ORD0179 | B180: Stethoscope | C180: North | D180: Catherine Lee | E180: 3 | F180: 750 | G180: 0 | H180: Yes | I180: 45165 | J180: =E180*F180*(1-G180/100) -> 2250 | K180: =ROUND(J180*15%,2) -> 337.5 | L180: =E180*F180 -> 2250 | M180: =DAY(I180) -> 27 | N180: =MONTH(I180) -> 8 | O180: =YEAR(I180) -> 2023 | P180: =IF(F180<500,"Low Price","High Price") -> High Price | Q180: =IF(J180>=AVERAGE(J:J),"Good","Bad") -> Bad | R180: =IF(G180>10,"High Discount",IF(G180=0,"No Discount","Low Discont")) -> No Discount | S180: =IF(AND(H180="Yes",G180>10),"High Priority Review",IF(H180="Yes","Low Priority Review","No Review Needed")) -> Low Priority Review | T180: =LEFT(C180,2) -> No
A181: ORD0180 | B181: Syringe Pack | C181: North | D181: Eva Brown | E181: 44 | F181: 500 | G181: 20 | H181: No | I181: 45196 | J181: =E181*F181*(1-G181/100) -> 17600 | K181: =ROUND(J181*15%,2) -> 2640 | L181: =E181*F181 -> 22000 | M181: =DAY(I181) -> 27 | N181: =MONTH(I181) -> 9 | O181: =YEAR(I181) -> 2023 | P181: =IF(F181<500,"Low Price","High Price") -> High Price | Q181: =IF(J181>=AVERAGE(J:J),"Good","Bad") -> Bad | R181: =IF(G181>10,"High Discount",IF(G181=0,"No Discount","Low Discont")) -> High Discount | S181: =IF(AND(H181="Yes",G181>10),"High Priority Review",IF(H181="Yes","Low Priority Review","No Review Needed")) -> No Review Needed | T181: =LEFT(C181,2) -> No
A182: ORD0181 | B182: Blood Test Kit | C182: South | D182: Henry Davis | E182: 36 | F182: 1750 | G182: 5 | H182: No | I182: 45257 | J182: =E182*F182*(1-G182/100) -> 59850 | K182: =ROUND(J182*15%,2) -> 8977.5 | L182: =E182*F182 -> 63000 | M182: =DAY(I182) -> 27 | N182: =MONTH(I182) -> 11 | O182: =YEAR(I182) -> 2023 | P182: =IF(F182<500,"Low Price","High Price") -> High Price | Q182: =IF(J182>=AVERAGE(J:J),"Good","Bad") -> Good | R182: =IF(G182>10,"High Discount",IF(G182=0,"No Discount","Low Discont")) -> Low Discont | S182: =IF(AND(H182="Yes",G182>10),"High Priority Review",IF(H182="Yes","Low Priority Review","No Review Needed")) -> No Review Needed | T182: =LEFT(C182,2) -> So
A183: ORD0182 | B183: Thermometer | C183: East | D183: Alice Johnson | E183: 16 | F183: 250 | G183: 10 | H183: Yes | I183: 45257 | J183: =E183*F183*(1-G183/100) -> 3600 | K183: =ROUND(J183*15%,2) -> 540 | L183: =E183*F183 -> 4000 | M183: =DAY(I183) -> 27 | N183: =MONTH(I183) -> 11 | O183: =YEAR(I183) -> 2023 | P183: =IF(F183<500,"Low Price","High Price") -> Low Price | Q183: =IF(J183>=AVERAGE(J:J),"Good","Bad") -> Bad | R183: =IF(G183>10,"High Discount",IF(G183=0,"No Discount","Low Discont")) -> Low Discont | S183: =IF(AND(H183="Yes",G183>10),"High Priority Review",IF(H183="Yes","Low Priority Review","No Review Needed")) -> Low Priority Review | T183: =LEFT(C183,2) -> Ea
A184: ORD0183 | B184: Stethoscope | C184: East | D184: Grace Kim | E184: 4 | F184: 750 | G184: 10 | H184: No | I184: 45287 | J184: =E184*F184*(1-G184/100) -> 2700 | K184: =ROUND(J184*15%,2) -> 405 | L184: =E184*F184 -> 3000 | M184: =DAY(I184) -> 27 | N184: =MONTH(I184) -> 12 | O184: =YEAR(I184) -> 2023 | P184: =IF(F184<500,"Low Price","High Price") -> High Price | Q184: =IF(J184>=AVERAGE(J:J),"Good","Bad") -> Bad | R184: =IF(G184>10,"High Discount",IF(G184=0,"No Discount","Low Discont")) -> Low Discont | S184: =IF(AND(H184="Yes",G184>10),"High Priority Review",IF(H184="Yes","Low Priority Review","No Review Needed")) -> No Review Needed | T184: =LEFT(C184,2) -> Ea
... A186: ORD0185 | B186: X-Ray Machine | C186: East | D186: Grace Kim | E186: 6 | F186: 5000 | G186: 15 | H186: No | I186: 44985 | J186: =E186*F186*(1-G186/100) -> 25500 | K186: =ROUND(J186*15%,2) -> 3825 | L186: =E186*F186 -> 30000 | M186: =DAY(I186) -> 28 | N186: =MONTH(I186) -> 2 | O186: =YEAR(I186) -> 2023 | P186: =IF(F186<500,"Low Price","High Price") -> High Price | Q186: =IF(J186>=AVERAGE(J:J),"Good","Bad") -> Good | R186: =IF(G186>10,"High Discount",IF(G186=0,"No Discount","Low Discont")) -> High Discount | S186: =IF(AND(H186="Yes",G186>10),"High Priority Review",IF(H186="Yes","Low Priority Review","No Review Needed")) -> No Review Needed | T186: =LEFT(C186,2) -> Ea
A187: ORD0186 | B187: Ultrasound Device | C187: South | E187: 5 | F187: 2000 | G187: 5 | H187: No | I187: 45013 | J187: =E187*F187*(1-G187/100) -> 9500 | K187: =ROUND(J187*15%,2) -> 1425 | L187: =E187*F187 -> 10000 | M187: =DAY(I187) -> 28 | N187: =MONTH(I187) -> 3 | O187: =YEAR(I187) -> 2023 | P187: =IF(F187<500,"Low Price","High Price") -> High Price | Q187: =IF(J187>=AVERAGE(J:J),"Good","Bad") -> Bad | R187: =IF(G187>10,"High Discount",IF(G187=0,"No Discount","Low Discont")) -> Low Discont | S187: =IF(AND(H187="Yes",G187>10),"High Priority Review",IF(H187="Yes","Low Priority Review","No Review Needed")) -> No Review Needed | T187: =LEFT(C187,2) -> So
A188: ORD0187 | B188: X-Ray Machine | C188: North | D188: Eva Brown | E188: 5 | F188: 5000 | G188: 5 | H188: No | I188: 45013 | J188: =E188*F188*(1-G188/100) -> 23750 | K188: =ROUND(J188*15%,2) -> 3562.5 | L188: =E188*F188 -> 25000 | M188: =DAY(I188) -> 28 | N188: =MONTH(I188) -> 3 | O188: =YEAR(I188) -> 2023 | P188: =IF(F188<500,"Low Price","High Price") -> High Price | Q188: =IF(J188>=AVERAGE(J:J),"Good","Bad") -> Good | R188: =IF(G188>10,"High Discount",IF(G188=0,"No Discount","Low Discont")) -> Low Discont | S188: =IF(AND(H188="Yes",G188>10),"High Priority Review",IF(H188="Yes","Low Priority Review","No Review Needed")) -> No Review Needed | T188: =LEFT(C188,2) -> No
A189: ORD0188 | B189: Thermometer | C189: East | D189: Alice Johnson | E189: 12 | F189: 250 | G189: 20 | H189: Yes | I189: 45074 | J189: =E189*F189*(1-G189/100) -> 2400 | K189: =ROUND(J189*15%,2) -> 360 | L189: =E189*F189 -> 3000 | M189: =DAY(I189) -> 28 | N189: =MONTH(I189) -> 5 | O189: =YEAR(I189) -> 2023 | P189: =IF(F189<500,"Low Price","High Price") -> Low Price | Q189: =IF(J189>=AVERAGE(J:J),"Good","Bad") -> Bad | R189: =IF(G189>10,"High Discount",IF(G189=0,"No Discount","Low Discont")) -> High Discount | S189: =IF(AND(H189="Yes",G189>10),"High Priority Review",IF(H189="Yes","Low Priority Review","No Review Needed")) -> High Priority Review | T189: =LEFT(C189,2) -> Ea
A190: ORD0189 | B190: X-Ray Machine | C190: North | D190: Catherine Lee | E190: 8 | F190: 5000 | G190: 10 | H190: No | I190: 45227 | J190: =E190*F190*(1-G190/100) -> 36000 | K190: =ROUND(J190*15%,2) -> 5400 | L190: =E190*F190 -> 40000 | M190: =DAY(I190) -> 28 | N190: =MONTH(I190) -> 10 | O190: =YEAR(I190) -> 2023 | P190: =IF(F190<500,"Low Price","High Price") -> High Price | Q190: =IF(J190>=AVERAGE(J:J),"Good","Bad") -> Good | R190: =IF(G190>10,"High Discount",IF(G190=0,"No Discount","Low Discont")) -> Low Discont | S190: =IF(AND(H190="Yes",G190>10),"High Priority Review",IF(H190="Yes","Low Priority Review","No Review Needed")) -> No Review Needed | T190: =LEFT(C190,2) -> No
...

Sheet Assessment Guidelines
A1: Sr No
B2: There are 3 types of questions which can be identified by the color coding
A3: C'0' | B3: Type 1 : Column Creation - These types of questions require you to create columns based on certain conditions - You need to create the additional columns in the 'Healthcare_Sales_Dataset' subsheet (For Now, column headers are provided so simply add the formulas) - Change the dropdown in 'Solution' column to 'Completed'
A4: 1'X' | B4: Type 2 : Calculation Based - These types of questions require you to do a calculation to find out a single value based on the question - You need to add the formula in the 'Solution' column against the question - Hints for which function(s) to use are provided for the calculation based questions
A5: M'0' | B5: Type 3 : Column Modification - These types of questions require you to modify existing columns based on certain conditions - You need to perform the expected modifications as per stated on the columns in the 'Healthcare_Sales_Dataset' subsheet - Hints for the modification will be provided - Change the dropdown in 'Solution' column to 'Completed'
B6: Save the file after completing all the questions in the 'Solution' Subsheet and upload as Solution file for the respective Module

Sheet Solution
A1: Sr No | B1: Question | C1: Solution | D1: Hint
A2: C1 | B2: Create Column TotalSales with this formula - TotalSales = UnitsSold × UnitPrice × (1 – Discount%) | C2: Completed
A3: 1A | B3: Calculate the Total Sales for all orders. | C3: =SUM(Healthcare_Sales_Dataset!J2:J201) -> 3918537.5 | D3: Use SUM( ) and then range referencing.
A4: 1B | B4: Total Number of orders | C4: =COUNTA(Healthcare_Sales_Dataset!A2:A201) -> 200 | D4: Use COUNTA( ) and then range referencing.
A5: 1C | B5: Find MIN of Total Sales | C5: =MIN(Healthcare_Sales_Dataset!J2:J201) -> 1350 | D5: Use MIN( ) and then range referencing.
A6: 1D | B6: Find MAX of Total Sales | C6: =MAX(Healthcare_Sales_Dataset!J2:J201) -> 90000 | D6: Use MAX( ) and then range referencing.
A7: 1E | B7: Find AVERAGE of Total Sales | C7: =AVERAGE(Healthcare_Sales_Dataset!J2:J201) -> 19592.688 | D7: Use AVERAGE( ) and then range referencing.
A8: C3 | B8: Create Column ExpectedSales (without discounts) with this formula - ExpectedSales = UnitsSold × UnitPrice | C8: Completed
A9: C2 | B9: Create a new column Deductions with this formula - Deductions = Tax + Commission (assume 10% Tax + 5% Commission) - Round deductions to 2 decimals using ROUND( ) | C9: Completed
A10: 1F | B10: Calculate the Total ExpectedSales | C10: =SUM(Healthcare_Sales_Dataset!L2:L201) -> 4387250 | D10: Use SUM( ) and then range referencing.
A11: 1G | B11: Calculate the Total Deductions | C11: =SUM(Healthcare_Sales_Dataset!K2:K201) -> 587780.72 | D11: Use SUM( ) and then range referencing.
A12: C4 | B12: Extract Day, Month, Year from OrderDate. | C12: Completed | D12: Create 3 separate columns for each
A13: C5 | B13: If unit price < 500 → tag as “Low Price”, else “High Price”. | C13: Completed | D13: Create column PriceTag with row wise computation using IF( ) function
A14: C6 | B14: Check if a sale ≥ average → mark as “Good”, else “Ok”. | C14: Completed | D14: Create column SalesTag with row wise computation using IF( ) function combined with AVERAGE( ) function
A15: C7 | B15: If discount > 10% → tag as “High Discount”, else if discount = 0%, tag as "No Discount", else “Low discount” | C15: Completed | D15: Create Column DiscountTag with row wise computation using nested IF( ) function
A16: C8 | B16: Flag orders for Review if ReturnStatus = “Yes” AND Discount > 10%. - If both conditions are met, mark the order as "High Priority Review" - If only the return status is "Yes," mark it as "Low Priority Review" - If neither condition is met, mark it as "No Review Needed" | C16: Completed | D16: Create Column ReturnTag with nested IF( ) function combined with AND( ) function
A17: C9 | B17: Generate region codes from the first 2 characters of Region. | C17: Completed | D17: Create column RegionCode with row wise computation using LEFT( ) function
